<?xml version="1.0"?>
<PluginData xmlns:xsd="http://www.w3.org/2001/XMLSchema" xmlns:xsi="http://www.w3.org/2001/XMLSchema-instance" xsi:type="GitHubPlugin">

  <Id>StarCpt/SE-TargetView</Id>
  <Author>StarCpt</Author>
  <FriendlyName>Target View</FriendlyName>
  <Tooltip>Shows a zoomed in view of the locked target in a picture-in-picture window.</Tooltip>

  <Description>Shows a zoomed in view of the locked target in a configurable picture-in-picture window.</Description>

  <Commit>55dfea38880f1b15f5effea7f09f61b523d90b57</Commit>

</PluginData>
